helpdev/__init__.py
helpdev/__main__.py
helpdev-0.7.1.dist-info/LICENSE.rst
helpdev-0.7.1.dist-info/METADATA
helpdev-0.7.1.dist-info/WHEEL
helpdev-0.7.1.dist-info/entry_points.txt
helpdev-0.7.1.dist-info/top_level.txt
helpdev-0.7.1.dist-info/RECORD
